freshcaller/__init__.py
freshdesk/__init__.py
freshworks-0.1.1.dist-info/LICENSE
freshworks-0.1.1.dist-info/METADATA
freshworks-0.1.1.dist-info/WHEEL
freshworks-0.1.1.dist-info/top_level.txt
freshworks-0.1.1.dist-info/RECORD
